download_center/__init__.py
download_center/config.py
download_center/requirements.txt
download_center/new_spider/__init__.py
download_center/new_spider/downloader/__init__.py
download_center/new_spider/downloader/config.py
download_center/new_spider/downloader/html_local_downloader.py
download_center/new_spider/spider/__init__.py
download_center/new_spider/spider/basespider.py
download_center/new_spider/spider/spider.py
download_center/new_spider/util/__init__.py
download_center/new_spider/util/ua_mobile_list.txt
download_center/new_spider/util/ua_pc_list.txt
download_center/new_spider/util/ua_spider_list.txt
download_center/new_spider/util/util_baidu.py
download_center/new_spider/util/util_baidu_relate.py
download_center/new_spider/util/util_md5.py
download_center/new_spider/util/util_ping.py
download_center/new_spider/util/util_proxy.py
download_center/new_spider/util/util_url.py
download_center/new_spider/util/util_useragent.py
download_center/store/__init__.py
download_center/store/baidu_cookies.py
download_center/store/config.py
download_center/store/py_store_mysql_pool.py
download_center/store/store_cache.py
download_center/store/store_es.py
download_center/store/store_es_v2.py
download_center/store/store_file.py
download_center/store/store_mongo.py
download_center/store/store_oss.py
download_center/util/__init__.py
download_center/util/py_util_basestore.py
download_center/util/util_log.py
download_center/util/util_log_v2.py
download_center-5.4.6.dist-info/METADATA
download_center-5.4.6.dist-info/WHEEL
download_center-5.4.6.dist-info/top_level.txt
download_center-5.4.6.dist-info/RECORD
